{"cameraMode":{"drawMode":0,"name":"Shaded","section":"Shading Mode"},"sceneLighting":true,"audioPlay":false,"sceneViewState":{"m_AlwaysRefresh":false,"showFog":true,"showSkybox":true,"showFlares":true,"showImageEffects":true,"showParticleSystems":true,"showVisualEffectGraphs":true,"m_FxEnabled":true},"in2DMode":false,"pivot":{"x":32.3863525390625,"y":-4.037817001342773,"z":15.166232109069825},"rotation":{"x":0.00277040246874094,"y":0.9923326969146729,"z":-0.12147709727287293,"w":0.022629709914326669},"size":23.080537796020509,"orthographic":false}